MANIFEST.in
Readme.rst
requirements.txt
setup.py
mdx_journal/__init__.py
mdx_journal/__meta__.py
mdx_journal.egg-info/PKG-INFO
mdx_journal.egg-info/SOURCES.txt
mdx_journal.egg-info/dependency_links.txt
mdx_journal.egg-info/not-zip-safe
mdx_journal.egg-info/requires.txt
mdx_journal.egg-info/top_level.txt