Metadata-Version: 1.1
Name: mdx-journal
Version: 0.1.4
Summary: Python-Markdown extension for annotating gthnk journal text files
Home-page: https://github.com/iandennismiller/mdx_journal
Author: Ian Dennis Miller
Author-email: iandennismiller@gmail.com
License: MIT
Platform: UNKNOWN
Classifier: Development Status :: 4 - Beta
Classifier: Operating System :: OS Independent
Classifier: License :: OSI Approved :: BSD License
Classifier: Intended Audience :: Developers
Classifier: Environment :: Web Environment
Classifier: Programming Language :: Python
Classifier: Topic :: Text Processing :: Filters
Classifier: Topic :: Text Processing :: Markup :: HTML
